playerok_requests_api/__init__.py
playerok_requests_api/chats.py
playerok_requests_api/deals.py
playerok_requests_api/items.py
playerok_requests_api/users.py
playerok_requests_api/utils.py
playerok_requests_api-0.1.6.dist-info/licenses/LICENSE
playerok_requests_api-0.1.6.dist-info/METADATA
playerok_requests_api-0.1.6.dist-info/WHEEL
playerok_requests_api-0.1.6.dist-info/top_level.txt
playerok_requests_api-0.1.6.dist-info/RECORD
