Metadata-Version: 2.4
Name: playerok-requests-api
Version: 0.1.6
Summary: Библиотека для взаимодействия с GraphQL API платформы Playerok
Author-email: lydyxxx <lydyxxxgt@gmail.com>
License-Expression: MIT
Project-URL: Homepage, https://github.com/lydyxxx/PlayerokRequestsApi
Project-URL: Bug Tracker, https://github.com/lydyxxx/PlayerokRequestsApi/issues
Classifier: Programming Language :: Python :: 3
Classifier: Programming Language :: Python :: 3.6
Classifier: Programming Language :: Python :: 3.7
Classifier: Programming Language :: Python :: 3.8
Classifier: Programming Language :: Python :: 3.9
Classifier: Programming Language :: Python :: 3.10
Classifier: Programming Language :: Python :: 3.11
Classifier: Operating System :: OS Independent
Requires-Python: >=3.6
License-File: LICENSE
Requires-Dist: wrapper-tls-requests==1.1.2
Dynamic: license-file
